README.txt
setup.py
collective/__init__.py
collective/__init__.pyc
collective.viewlet.references.egg-info/PKG-INFO
collective.viewlet.references.egg-info/SOURCES.txt
collective.viewlet.references.egg-info/dependency_links.txt
collective.viewlet.references.egg-info/entry_points.txt
collective.viewlet.references.egg-info/namespace_packages.txt
collective.viewlet.references.egg-info/not-zip-safe
collective.viewlet.references.egg-info/requires.txt
collective.viewlet.references.egg-info/top_level.txt
collective/viewlet/__init__.py
collective/viewlet/__init__.pyc
collective/viewlet/references/__init__.py
collective/viewlet/references/configure.zcml
collective/viewlet/references/profiles.zcml
collective/viewlet/references/setuphandlers.py
collective/viewlet/references/tests.py
collective/viewlet/references/version.txt
collective/viewlet/references/browser/__init__.py
collective/viewlet/references/browser/configure.zcml
collective/viewlet/references/browser/references.pt
collective/viewlet/references/browser/references.py
collective/viewlet/references/profiles/default/metadata.xml
collective/viewlet/references/profiles/default/propertiestool.xml
collective/viewlet/references/profiles/default/references_various.txt
collective/viewlet/references/profiles/uninstall/setuphandlers.py
docs/HISTORY.txt
docs/INSTALL.txt
docs/LICENSE.GPL
docs/LICENSE.txt