Metadata-Version: 1.0
Name: collective.viewlet.references
Version: 0.5
Summary: Viewlet that shows all the references to the current article including back references
Home-page: https://svn.v2.nl/plone/collective.viewlet.references
Author: David Jonas
Author-email: david@v2.nl
License: GPL
Keywords: plone collective viewlet references details
Platform: UNKNOWN
Classifier: Framework :: Plone
Classifier: Programming Language :: Python
